{
  "summary": {
    "instances": 270,
    "feasible": 187,
    "infeasible": 83,
    "unknown": 0,
    "avg_makespan": 45.657754010695186,
    "avg_ratio": 1.330973992667301,
    "avg_runtime_seconds": 0.32800854533711066,
    "best_ratio": 1.0,
    "worst_ratio": 2.9166666666666665
  },
  "results": [
    {
      "instance": "PSP1",
      "status": "feasible",
      "makespan": 26,
      "temporal_lower_bound": 26,
      "ratio": 1.0,
      "runtime_seconds": 0.5503879579991917,
      "restarts": 512
    },
    {
      "instance": "PSP10",
      "status": "feasible",
      "makespan": 36,
      "temporal_lower_bound": 18,
      "ratio": 2.0,
      "runtime_seconds": 0.558401958001923,
      "restarts": 228
    },
    {
      "instance": "PSP100",
      "status": "feasible",
      "makespan": 44,
      "temporal_lower_bound": 31,
      "ratio": 1.4193548387096775,
      "runtime_seconds": 0.5529929590011307,
      "restarts": 306
    },
    {
      "instance": "PSP101",
      "status": "feasible",
      "makespan": 62,
      "temporal_lower_bound": 46,
      "ratio": 1.3478260869565217,
      "runtime_seconds": 0.5534839159990952,
      "restarts": 336
    },
    {
      "instance": "PSP102",
      "status": "feasible",
      "makespan": 52,
      "temporal_lower_bound": 35,
      "ratio": 1.4857142857142858,
      "runtime_seconds": 0.2029112919990439,
      "restarts": 0
    },
    {
      "instance": "PSP103",
      "status": "feasible",
      "makespan": 18,
      "temporal_lower_bound": 14,
      "ratio": 1.2857142857142858,
      "runtime_seconds": 0.5505972079990897,
      "restarts": 737
    },
    {
      "instance": "PSP104",
      "status": "feasible",
      "makespan": 32,
      "temporal_lower_bound": 26,
      "ratio": 1.2307692307692308,
      "runtime_seconds": 0.20235737500115647,
      "restarts": 0
    },
    {
      "instance": "PSP105",
      "status": "feasible",
      "makespan": 26,
      "temporal_lower_bound": 18,
      "ratio": 1.4444444444444444,
      "runtime_seconds": 0.20319975000165869,
      "restarts": 0
    },
    {
      "instance": "PSP106",
      "status": "feasible",
      "makespan": 51,
      "temporal_lower_bound": 41,
      "ratio": 1.2439024390243902,
      "runtime_seconds": 0.5506591670018679,
      "restarts": 393
    },
    {
      "instance": "PSP107",
      "status": "feasible",
      "makespan": 46,
      "temporal_lower_bound": 38,
      "ratio": 1.2105263157894737,
      "runtime_seconds": 0.20425604100091732,
      "restarts": 0
    },
    {
      "instance": "PSP108",
      "status": "infeasible",
      "makespan": null,
      "temporal_lower_bound": 37,
      "ratio": null,
      "runtime_seconds": 1.654200241318904e-05,
      "restarts": 0
    },
    {
      "instance": "PSP109",
      "status": "infeasible",
      "makespan": null,
      "temporal_lower_bound": 37,
      "ratio": null,
      "runtime_seconds": 5.429199882200919e-05,
      "restarts": 0
    },
    {
      "instance": "PSP11",
      "status": "feasible",
      "makespan": 31,
      "temporal_lower_bound": 17,
      "ratio": 1.8235294117647058,
      "runtime_seconds": 0.5533768749992305,
      "restarts": 311
    },
    {
      "instance": "PSP110",
      "status": "feasible",
      "makespan": 58,
      "temporal_lower_bound": 45,
      "ratio": 1.288888888888889,
      "runtime_seconds": 0.5510913329999312,
      "restarts": 380
    },
    {
      "instance": "PSP111",
      "status": "feasible",
      "makespan": 33,
      "temporal_lower_bound": 30,
      "ratio": 1.1,
      "runtime_seconds": 0.5525029999989783,
      "restarts": 1
    },
    {
      "instance": "PSP112",
      "status": "infeasible",
      "makespan": null,
      "temporal_lower_bound": 28,
      "ratio": null,
      "runtime_seconds": 1.6916997992666438e-05,
      "restarts": 0
    },
    {
      "instance": "PSP113",
      "status": "feasible",
      "makespan": 22,
      "temporal_lower_bound": 22,
      "ratio": 1.0,
      "runtime_seconds": 0.5517177499968966,
      "restarts": 571
    },
    {
      "instance": "PSP114",
      "status": "feasible",
      "makespan": 41,
      "temporal_lower_bound": 36,
      "ratio": 1.1388888888888888,
      "runtime_seconds": 0.5508580000023358,
      "restarts": 511
    },
    {
      "instance": "PSP115",
      "status": "feasible",
      "makespan": 41,
      "temporal_lower_bound": 40,
      "ratio": 1.025,
      "runtime_seconds": 0.5505704170027457,
      "restarts": 498
    },
    {
      "instance": "PSP116",
      "status": "feasible",
      "makespan": 16,
      "temporal_lower_bound": 13,
      "ratio": 1.2307692307692308,
      "runtime_seconds": 0.5505439589978778,
      "restarts": 596
    },
    {
      "instance": "PSP117",
      "status": "feasible",
      "makespan": 27,
      "temporal_lower_bound": 22,
      "ratio": 1.2272727272727273,
      "runtime_seconds": 0.550828041999921,
      "restarts": 488
    },
    {
      "instance": "PSP118",
      "status": "infeasible",
      "makespan": null,
      "temporal_lower_bound": 29,
      "ratio": null,
      "runtime_seconds": 6.120799662312493e-05,
      "restarts": 0
    },
    {
      "instance": "PSP119",
      "status": "infeasible",
      "makespan": null,
      "temporal_lower_bound": 40,
      "ratio": null,
      "runtime_seconds": 1.4666999049950391e-05,
      "restarts": 0
    },
    {
      "instance": "PSP12",
      "status": "infeasible",
      "makespan": null,
      "temporal_lower_bound": 31,
      "ratio": null,
      "runtime_seconds": 3.941600152757019e-05,
      "restarts": 0
    },
    {
      "instance": "PSP120",
      "status": "feasible",
      "makespan": 38,
      "temporal_lower_bound": 38,
      "ratio": 1.0,
      "runtime_seconds": 0.5603390409996791,
      "restarts": 1
    },
    {
      "instance": "PSP121",
      "status": "feasible",
      "makespan": 57,
      "temporal_lower_bound": 34,
      "ratio": 1.6764705882352942,
      "runtime_seconds": 0.20479070800138288,
      "restarts": 0
    },
    {
      "instance": "PSP122",
      "status": "infeasible",
      "makespan": null,
      "temporal_lower_bound": 60,
      "ratio": null,
      "runtime_seconds": 5.295800292515196e-05,
      "restarts": 0
    },
    {
      "instance": "PSP123",
      "status": "infeasible",
      "makespan": null,
      "temporal_lower_bound": 29,
      "ratio": null,
      "runtime_seconds": 4.9540998588781804e-05,
      "restarts": 0
    },
    {
      "instance": "PSP124",
      "status": "infeasible",
      "makespan": null,
      "temporal_lower_bound": 36,
      "ratio": null,
      "runtime_seconds": 5.1540999265853316e-05,
      "restarts": 0
    },
    {
      "instance": "PSP125",
      "status": "infeasible",
      "makespan": null,
      "temporal_lower_bound": 42,
      "ratio": null,
      "runtime_seconds": 0.20404475000032107,
      "restarts": 0
    },
    {
      "instance": "PSP126",
      "status": "feasible",
      "makespan": 70,
      "temporal_lower_bound": 33,
      "ratio": 2.121212121212121,
      "runtime_seconds": 0.20348458399894298,
      "restarts": 0
    },
    {
      "instance": "PSP127",
      "status": "feasible",
      "makespan": 44,
      "temporal_lower_bound": 26,
      "ratio": 1.6923076923076923,
      "runtime_seconds": 0.5640316250028263,
      "restarts": 269
    },
    {
      "instance": "PSP128",
      "status": "feasible",
      "makespan": 49,
      "temporal_lower_bound": 40,
      "ratio": 1.225,
      "runtime_seconds": 0.5511259580016485,
      "restarts": 335
    },
    {
      "instance": "PSP129",
      "status": "feasible",
      "makespan": 53,
      "temporal_lower_bound": 24,
      "ratio": 2.2083333333333335,
      "runtime_seconds": 0.204411082999286,
      "restarts": 0
    },
    {
      "instance": "PSP13",
      "status": "feasible",
      "makespan": 42,
      "temporal_lower_bound": 30,
      "ratio": 1.4,
      "runtime_seconds": 0.5547333750000689,
      "restarts": 355
    },
    {
      "instance": "PSP130",
      "status": "feasible",
      "makespan": 45,
      "temporal_lower_bound": 44,
      "ratio": 1.0227272727272727,
      "runtime_seconds": 0.551392624998698,
      "restarts": 329
    },
    {
      "instance": "PSP131",
      "status": "feasible",
      "makespan": 46,
      "temporal_lower_bound": 41,
      "ratio": 1.1219512195121952,
      "runtime_seconds": 0.551416957998299,
      "restarts": 413
    },
    {
      "instance": "PSP132",
      "status": "feasible",
      "makespan": 37,
      "temporal_lower_bound": 29,
      "ratio": 1.2758620689655173,
      "runtime_seconds": 0.5618345000002591,
      "restarts": 299
    },
    {
      "instance": "PSP133",
      "status": "feasible",
      "makespan": 41,
      "temporal_lower_bound": 35,
      "ratio": 1.1714285714285715,
      "runtime_seconds": 0.5506843330003903,
      "restarts": 508
    },
    {
      "instance": "PSP134",
      "status": "feasible",
      "makespan": 29,
      "temporal_lower_bound": 23,
      "ratio": 1.2608695652173914,
      "runtime_seconds": 0.20430887499969685,
      "restarts": 0
    },
    {
      "instance": "PSP135",
      "status": "feasible",
      "makespan": 67,
      "temporal_lower_bound": 55,
      "ratio": 1.2181818181818183,
      "runtime_seconds": 0.5569232910020219,
      "restarts": 261
    },
    {
      "instance": "PSP136",
      "status": "infeasible",
      "makespan": null,
      "temporal_lower_bound": 46,
      "ratio": null,
      "runtime_seconds": 4.7500001528533176e-05,
      "restarts": 0
    },
    {
      "instance": "PSP137",
      "status": "feasible",
      "makespan": 44,
      "temporal_lower_bound": 41,
      "ratio": 1.0731707317073171,
      "runtime_seconds": 0.5506872500009194,
      "restarts": 485
    },
    {
      "instance": "PSP138",
      "status": "feasible",
      "makespan": 45,
      "temporal_lower_bound": 29,
      "ratio": 1.5517241379310345,
      "runtime_seconds": 0.5608040840015747,
      "restarts": 1
    },
    {
      "instance": "PSP139",
      "status": "feasible",
      "makespan": 55,
      "temporal_lower_bound": 34,
      "ratio": 1.6176470588235294,
      "runtime_seconds": 0.5514874590007821,
      "restarts": 289
    },
    {
      "instance": "PSP14",
      "status": "infeasible",
      "makespan": null,
      "temporal_lower_bound": 31,
      "ratio": null,
      "runtime_seconds": 4.7375000576721504e-05,
      "restarts": 0
    },
    {
      "instance": "PSP140",
      "status": "infeasible",
      "makespan": null,
      "temporal_lower_bound": 34,
      "ratio": null,
      "runtime_seconds": 4.7790999815333635e-05,
      "restarts": 0
    },
    {
      "instance": "PSP141",
      "status": "infeasible",
      "makespan": null,
      "temporal_lower_bound": 33,
      "ratio": null,
      "runtime_seconds": 5.4874999477760866e-05,
      "restarts": 0
    },
    {
      "instance": "PSP142",
      "status": "feasible",
      "makespan": 53,
      "temporal_lower_bound": 47,
      "ratio": 1.127659574468085,
      "runtime_seconds": 0.5509212090000801,
      "restarts": 423
    },
    {
      "instance": "PSP143",
      "status": "feasible",
      "makespan": 39,
      "temporal_lower_bound": 32,
      "ratio": 1.21875,
      "runtime_seconds": 0.5512111669995647,
      "restarts": 392
    },
    {
      "instance": "PSP144",
      "status": "feasible",
      "makespan": 31,
      "temporal_lower_bound": 31,
      "ratio": 1.0,
      "runtime_seconds": 0.0005214159973547794,
      "restarts": 1
    },
    {
      "instance": "PSP145",
      "status": "infeasible",
      "makespan": null,
      "temporal_lower_bound": 36,
      "ratio": null,
      "runtime_seconds": 1.5000001440057531e-05,
      "restarts": 0
    },
    {
      "instance": "PSP146",
      "status": "feasible",
      "makespan": 32,
      "temporal_lower_bound": 32,
      "ratio": 1.0,
      "runtime_seconds": 0.0004501250004977919,
      "restarts": 1
    },
    {
      "instance": "PSP147",
      "status": "feasible",
      "makespan": 45,
      "temporal_lower_bound": 42,
      "ratio": 1.0714285714285714,
      "runtime_seconds": 0.5505736669983889,
      "restarts": 566
    },
    {
      "instance": "PSP148",
      "status": "feasible",
      "makespan": 43,
      "temporal_lower_bound": 38,
      "ratio": 1.131578947368421,
      "runtime_seconds": 0.551282791999256,
      "restarts": 349
    },
    {
      "instance": "PSP149",
      "status": "feasible",
      "makespan": 25,
      "temporal_lower_bound": 15,
      "ratio": 1.6666666666666667,
      "runtime_seconds": 0.5518682500005525,
      "restarts": 329
    },
    {
      "instance": "PSP15",
      "status": "feasible",
      "makespan": 39,
      "temporal_lower_bound": 23,
      "ratio": 1.6956521739130435,
      "runtime_seconds": 0.5620052919985028,
      "restarts": 1
    },
    {
      "instance": "PSP150",
      "status": "feasible",
      "makespan": 29,
      "temporal_lower_bound": 26,
      "ratio": 1.1153846153846154,
      "runtime_seconds": 0.5505684999989171,
      "restarts": 481
    },
    {
      "instance": "PSP151",
      "status": "feasible",
      "makespan": 78,
      "temporal_lower_bound": 66,
      "ratio": 1.1818181818181819,
      "runtime_seconds": 0.5594634579974809,
      "restarts": 1
    },
    {
      "instance": "PSP152",
      "status": "infeasible",
      "makespan": null,
      "temporal_lower_bound": 48,
      "ratio": null,
      "runtime_seconds": 6.0165999457240105e-05,
      "restarts": 0
    },
    {
      "instance": "PSP153",
      "status": "feasible",
      "makespan": 53,
      "temporal_lower_bound": 28,
      "ratio": 1.8928571428571428,
      "runtime_seconds": 0.2327122499991674,
      "restarts": 0
    },
    {
      "instance": "PSP154",
      "status": "infeasible",
      "makespan": null,
      "temporal_lower_bound": 39,
      "ratio": null,
      "runtime_seconds": 5.824999971082434e-05,
      "restarts": 0
    },
    {
      "instance": "PSP155",
      "status": "feasible",
      "makespan": 52,
      "temporal_lower_bound": 35,
      "ratio": 1.4857142857142858,
      "runtime_seconds": 0.5548899169989454,
      "restarts": 392
    },
    {
      "instance": "PSP156",
      "status": "feasible",
      "makespan": 66,
      "temporal_lower_bound": 54,
      "ratio": 1.2222222222222223,
      "runtime_seconds": 0.5698645419979584,
      "restarts": 262
    },
    {
      "instance": "PSP157",
      "status": "feasible",
      "makespan": 61,
      "temporal_lower_bound": 35,
      "ratio": 1.7428571428571429,
      "runtime_seconds": 0.5869222910005192,
      "restarts": 1
    },
    {
      "instance": "PSP158",
      "status": "feasible",
      "makespan": 59,
      "temporal_lower_bound": 33,
      "ratio": 1.7878787878787878,
      "runtime_seconds": 0.57013829099742,
      "restarts": 1
    },
    {
      "instance": "PSP159",
      "status": "infeasible",
      "makespan": null,
      "temporal_lower_bound": 47,
      "ratio": null,
      "runtime_seconds": 6.174999725772068e-05,
      "restarts": 0
    },
    {
      "instance": "PSP16",
      "status": "feasible",
      "makespan": 30,
      "temporal_lower_bound": 24,
      "ratio": 1.25,
      "runtime_seconds": 0.5511751249978261,
      "restarts": 457
    },
    {
      "instance": "PSP160",
      "status": "infeasible",
      "makespan": null,
      "temporal_lower_bound": 27,
      "ratio": null,
      "runtime_seconds": 0.20467520800229977,
      "restarts": 0
    },
    {
      "instance": "PSP161",
      "status": "feasible",
      "makespan": 29,
      "temporal_lower_bound": 17,
      "ratio": 1.7058823529411764,
      "runtime_seconds": 0.5519105830026092,
      "restarts": 337
    },
    {
      "instance": "PSP162",
      "status": "infeasible",
      "makespan": null,
      "temporal_lower_bound": 20,
      "ratio": null,
      "runtime_seconds": 6.12499970884528e-05,
      "restarts": 0
    },
    {
      "instance": "PSP163",
      "status": "feasible",
      "makespan": 53,
      "temporal_lower_bound": 33,
      "ratio": 1.606060606060606,
      "runtime_seconds": 0.21028658300201641,
      "restarts": 0
    },
    {
      "instance": "PSP164",
      "status": "infeasible",
      "makespan": null,
      "temporal_lower_bound": 40,
      "ratio": null,
      "runtime_seconds": 6.220800059963949e-05,
      "restarts": 0
    },
    {
      "instance": "PSP165",
      "status": "infeasible",
      "makespan": null,
      "temporal_lower_bound": 32,
      "ratio": null,
      "runtime_seconds": 4.5916000090073794e-05,
      "restarts": 0
    },
    {
      "instance": "PSP166",
      "status": "feasible",
      "makespan": 34,
      "temporal_lower_bound": 32,
      "ratio": 1.0625,
      "runtime_seconds": 0.2041876660005073,
      "restarts": 0
    },
    {
      "instance": "PSP167",
      "status": "feasible",
      "makespan": 50,
      "temporal_lower_bound": 26,
      "ratio": 1.9230769230769231,
      "runtime_seconds": 0.5514982499989856,
      "restarts": 208
    },
    {
      "instance": "PSP168",
      "status": "infeasible",
      "makespan": null,
      "temporal_lower_bound": 26,
      "ratio": null,
      "runtime_seconds": 6.508299702545628e-05,
      "restarts": 0
    },
    {
      "instance": "PSP169",
      "status": "infeasible",
      "makespan": null,
      "temporal_lower_bound": 54,
      "ratio": null,
      "runtime_seconds": 1.0957999620586634e-05,
      "restarts": 0
    },
    {
      "instance": "PSP17",
      "status": "infeasible",
      "makespan": null,
      "temporal_lower_bound": 36,
      "ratio": null,
      "runtime_seconds": 1.5624998923158273e-05,
      "restarts": 0
    },
    {
      "instance": "PSP170",
      "status": "feasible",
      "makespan": 69,
      "temporal_lower_bound": 52,
      "ratio": 1.3269230769230769,
      "runtime_seconds": 0.5571033750020433,
      "restarts": 217
    },
    {
      "instance": "PSP171",
      "status": "feasible",
      "makespan": 33,
      "temporal_lower_bound": 33,
      "ratio": 1.0,
      "runtime_seconds": 0.0003949999991164077,
      "restarts": 1
    },
    {
      "instance": "PSP172",
      "status": "feasible",
      "makespan": 37,
      "temporal_lower_bound": 37,
      "ratio": 1.0,
      "runtime_seconds": 0.5503472909986158,
      "restarts": 539
    },
    {
      "instance": "PSP173",
      "status": "feasible",
      "makespan": 32,
      "temporal_lower_bound": 32,
      "ratio": 1.0,
      "runtime_seconds": 0.00038891599979251623,
      "restarts": 1
    },
    {
      "instance": "PSP174",
      "status": "feasible",
      "makespan": 50,
      "temporal_lower_bound": 50,
      "ratio": 1.0,
      "runtime_seconds": 0.5504713750015071,
      "restarts": 534
    },
    {
      "instance": "PSP175",
      "status": "feasible",
      "makespan": 19,
      "temporal_lower_bound": 16,
      "ratio": 1.1875,
      "runtime_seconds": 0.5519981249999546,
      "restarts": 617
    },
    {
      "instance": "PSP176",
      "status": "feasible",
      "makespan": 57,
      "temporal_lower_bound": 55,
      "ratio": 1.0363636363636364,
      "runtime_seconds": 0.5540252920000057,
      "restarts": 488
    },
    {
      "instance": "PSP177",
      "status": "feasible",
      "makespan": 62,
      "temporal_lower_bound": 62,
      "ratio": 1.0,
      "runtime_seconds": 0.00045937500181025825,
      "restarts": 1
    },
    {
      "instance": "PSP178",
      "status": "feasible",
      "makespan": 55,
      "temporal_lower_bound": 55,
      "ratio": 1.0,
      "runtime_seconds": 0.0005624580007861368,
      "restarts": 1
    },
    {
      "instance": "PSP179",
      "status": "feasible",
      "makespan": 33,
      "temporal_lower_bound": 28,
      "ratio": 1.1785714285714286,
      "runtime_seconds": 0.5506631669995841,
      "restarts": 612
    },
    {
      "instance": "PSP18",
      "status": "feasible",
      "makespan": 27,
      "temporal_lower_bound": 26,
      "ratio": 1.0384615384615385,
      "runtime_seconds": 0.5516436670004623,
      "restarts": 362
    },
    {
      "instance": "PSP180",
      "status": "infeasible",
      "makespan": null,
      "temporal_lower_bound": 40,
      "ratio": null,
      "runtime_seconds": 6.270799713092856e-05,
      "restarts": 0
    },
    {
      "instance": "PSP181",
      "status": "feasible",
      "makespan": 46,
      "temporal_lower_bound": 36,
      "ratio": 1.2777777777777777,
      "runtime_seconds": 0.5516390829980082,
      "restarts": 336
    },
    {
      "instance": "PSP182",
      "status": "feasible",
      "makespan": 44,
      "temporal_lower_bound": 37,
      "ratio": 1.1891891891891893,
      "runtime_seconds": 0.55093358400336,
      "restarts": 519
    },
    {
      "instance": "PSP183",
      "status": "feasible",
      "makespan": 40,
      "temporal_lower_bound": 24,
      "ratio": 1.6666666666666667,
      "runtime_seconds": 0.5564384159988549,
      "restarts": 1
    },
    {
      "instance": "PSP184",
      "status": "infeasible",
      "makespan": null,
      "temporal_lower_bound": 30,
      "ratio": null,
      "runtime_seconds": 0.2029213339992566,
      "restarts": 0
    },
    {
      "instance": "PSP185",
      "status": "infeasible",
      "makespan": null,
      "temporal_lower_bound": 30,
      "ratio": null,
      "runtime_seconds": 6.341700282064267e-05,
      "restarts": 0
    },
    {
      "instance": "PSP186",
      "status": "feasible",
      "makespan": 30,
      "temporal_lower_bound": 21,
      "ratio": 1.4285714285714286,
      "runtime_seconds": 0.5507834580021154,
      "restarts": 417
    },
    {
      "instance": "PSP187",
      "status": "feasible",
      "makespan": 77,
      "temporal_lower_bound": 64,
      "ratio": 1.203125,
      "runtime_seconds": 0.20330791699961992,
      "restarts": 0
    },
    {
      "instance": "PSP188",
      "status": "feasible",
      "makespan": 38,
      "temporal_lower_bound": 35,
      "ratio": 1.0857142857142856,
      "runtime_seconds": 0.5547535410005366,
      "restarts": 496
    },
    {
      "instance": "PSP189",
      "status": "feasible",
      "makespan": 33,
      "temporal_lower_bound": 32,
      "ratio": 1.03125,
      "runtime_seconds": 0.5506493329994555,
      "restarts": 558
    },
    {
      "instance": "PSP19",
      "status": "feasible",
      "makespan": 29,
      "temporal_lower_bound": 20,
      "ratio": 1.45,
      "runtime_seconds": 0.553454791999684,
      "restarts": 1
    },
    {
      "instance": "PSP190",
      "status": "feasible",
      "makespan": 53,
      "temporal_lower_bound": 49,
      "ratio": 1.0816326530612246,
      "runtime_seconds": 0.5505505000000994,
      "restarts": 619
    },
    {
      "instance": "PSP191",
      "status": "feasible",
      "makespan": 78,
      "temporal_lower_bound": 65,
      "ratio": 1.2,
      "runtime_seconds": 0.5507757080013107,
      "restarts": 344
    },
    {
      "instance": "PSP192",
      "status": "feasible",
      "makespan": 53,
      "temporal_lower_bound": 46,
      "ratio": 1.1521739130434783,
      "runtime_seconds": 0.5512510419976024,
      "restarts": 339
    },
    {
      "instance": "PSP193",
      "status": "infeasible",
      "makespan": null,
      "temporal_lower_bound": 81,
      "ratio": null,
      "runtime_seconds": 5.804200191050768e-05,
      "restarts": 0
    },
    {
      "instance": "PSP194",
      "status": "feasible",
      "makespan": 39,
      "temporal_lower_bound": 36,
      "ratio": 1.0833333333333333,
      "runtime_seconds": 0.557963084000221,
      "restarts": 1
    },
    {
      "instance": "PSP195",
      "status": "infeasible",
      "makespan": null,
      "temporal_lower_bound": 49,
      "ratio": null,
      "runtime_seconds": 1.424999936716631e-05,
      "restarts": 0
    },
    {
      "instance": "PSP196",
      "status": "infeasible",
      "makespan": null,
      "temporal_lower_bound": 82,
      "ratio": null,
      "runtime_seconds": 1.3374999980442226e-05,
      "restarts": 0
    },
    {
      "instance": "PSP197",
      "status": "infeasible",
      "makespan": null,
      "temporal_lower_bound": 64,
      "ratio": null,
      "runtime_seconds": 5.087500176159665e-05,
      "restarts": 0
    },
    {
      "instance": "PSP198",
      "status": "infeasible",
      "makespan": null,
      "temporal_lower_bound": 51,
      "ratio": null,
      "runtime_seconds": 1.2290998711250722e-05,
      "restarts": 0
    },
    {
      "instance": "PSP199",
      "status": "feasible",
      "makespan": 45,
      "temporal_lower_bound": 35,
      "ratio": 1.2857142857142858,
      "runtime_seconds": 0.5505497919984919,
      "restarts": 433
    },
    {
      "instance": "PSP2",
      "status": "infeasible",
      "makespan": null,
      "temporal_lower_bound": 24,
      "ratio": null,
      "runtime_seconds": 4.0916998841566965e-05,
      "restarts": 0
    },
    {
      "instance": "PSP20",
      "status": "feasible",
      "makespan": 40,
      "temporal_lower_bound": 30,
      "ratio": 1.3333333333333333,
      "runtime_seconds": 0.558632291998947,
      "restarts": 319
    },
    {
      "instance": "PSP200",
      "status": "feasible",
      "makespan": 46,
      "temporal_lower_bound": 43,
      "ratio": 1.069767441860465,
      "runtime_seconds": 0.5507568749999336,
      "restarts": 587
    },
    {
      "instance": "PSP201",
      "status": "infeasible",
      "makespan": null,
      "temporal_lower_bound": 43,
      "ratio": null,
      "runtime_seconds": 1.5459001588169485e-05,
      "restarts": 0
    },
    {
      "instance": "PSP202",
      "status": "infeasible",
      "makespan": null,
      "temporal_lower_bound": 65,
      "ratio": null,
      "runtime_seconds": 1.541700112284161e-05,
      "restarts": 0
    },
    {
      "instance": "PSP203",
      "status": "feasible",
      "makespan": 44,
      "temporal_lower_bound": 43,
      "ratio": 1.0232558139534884,
      "runtime_seconds": 0.5503719580010511,
      "restarts": 745
    },
    {
      "instance": "PSP204",
      "status": "infeasible",
      "makespan": null,
      "temporal_lower_bound": 39,
      "ratio": null,
      "runtime_seconds": 5.295799928717315e-05,
      "restarts": 0
    },
    {
      "instance": "PSP205",
      "status": "infeasible",
      "makespan": null,
      "temporal_lower_bound": 13,
      "ratio": null,
      "runtime_seconds": 5.0416001613484696e-05,
      "restarts": 0
    },
    {
      "instance": "PSP206",
      "status": "feasible",
      "makespan": 53,
      "temporal_lower_bound": 43,
      "ratio": 1.2325581395348837,
      "runtime_seconds": 0.5506726670028002,
      "restarts": 387
    },
    {
      "instance": "PSP207",
      "status": "feasible",
      "makespan": 66,
      "temporal_lower_bound": 65,
      "ratio": 1.0153846153846153,
      "runtime_seconds": 0.20412441699954798,
      "restarts": 0
    },
    {
      "instance": "PSP208",
      "status": "infeasible",
      "makespan": null,
      "temporal_lower_bound": 48,
      "ratio": null,
      "runtime_seconds": 1.5083998732734472e-05,
      "restarts": 0
    },
    {
      "instance": "PSP209",
      "status": "infeasible",
      "makespan": null,
      "temporal_lower_bound": 40,
      "ratio": null,
      "runtime_seconds": 1.5583002095809206e-05,
      "restarts": 0
    },
    {
      "instance": "PSP21",
      "status": "feasible",
      "makespan": 37,
      "temporal_lower_bound": 30,
      "ratio": 1.2333333333333334,
      "runtime_seconds": 0.5505595419999736,
      "restarts": 562
    },
    {
      "instance": "PSP210",
      "status": "feasible",
      "makespan": 44,
      "temporal_lower_bound": 44,
      "ratio": 1.0,
      "runtime_seconds": 0.00038295799822662957,
      "restarts": 1
    },
    {
      "instance": "PSP211",
      "status": "infeasible",
      "makespan": null,
      "temporal_lower_bound": 52,
      "ratio": null,
      "runtime_seconds": 7.92499995441176e-05,
      "restarts": 0
    },
    {
      "instance": "PSP212",
      "status": "feasible",
      "makespan": 66,
      "temporal_lower_bound": 56,
      "ratio": 1.1785714285714286,
      "runtime_seconds": 0.5507730839999567,
      "restarts": 398
    },
    {
      "instance": "PSP213",
      "status": "feasible",
      "makespan": 53,
      "temporal_lower_bound": 49,
      "ratio": 1.0816326530612246,
      "runtime_seconds": 0.5511259170016274,
      "restarts": 408
    },
    {
      "instance": "PSP214",
      "status": "feasible",
      "makespan": 37,
      "temporal_lower_bound": 25,
      "ratio": 1.48,
      "runtime_seconds": 0.5519637920006062,
      "restarts": 519
    },
    {
      "instance": "PSP215",
      "status": "infeasible",
      "makespan": null,
      "temporal_lower_bound": 35,
      "ratio": null,
      "runtime_seconds": 6.162499994388781e-05,
      "restarts": 0
    },
    {
      "instance": "PSP216",
      "status": "feasible",
      "makespan": 45,
      "temporal_lower_bound": 34,
      "ratio": 1.3235294117647058,
      "runtime_seconds": 0.5519327500005602,
      "restarts": 198
    },
    {
      "instance": "PSP217",
      "status": "feasible",
      "makespan": 74,
      "temporal_lower_bound": 58,
      "ratio": 1.2758620689655173,
      "runtime_seconds": 0.551715833000344,
      "restarts": 222
    },
    {
      "instance": "PSP218",
      "status": "infeasible",
      "makespan": null,
      "temporal_lower_bound": 28,
      "ratio": null,
      "runtime_seconds": 6.229100108612329e-05,
      "restarts": 0
    },
    {
      "instance": "PSP219",
      "status": "feasible",
      "makespan": 59,
      "temporal_lower_bound": 52,
      "ratio": 1.1346153846153846,
      "runtime_seconds": 0.5571392499987269,
      "restarts": 148
    },
    {
      "instance": "PSP22",
      "status": "feasible",
      "makespan": 38,
      "temporal_lower_bound": 29,
      "ratio": 1.3103448275862069,
      "runtime_seconds": 0.5555791670012695,
      "restarts": 136
    },
    {
      "instance": "PSP220",
      "status": "infeasible",
      "makespan": null,
      "temporal_lower_bound": 64,
      "ratio": null,
      "runtime_seconds": 6.4208001276711e-05,
      "restarts": 0
    },
    {
      "instance": "PSP221",
      "status": "feasible",
      "makespan": 39,
      "temporal_lower_bound": 24,
      "ratio": 1.625,
      "runtime_seconds": 0.5597257080007694,
      "restarts": 1
    },
    {
      "instance": "PSP222",
      "status": "feasible",
      "makespan": 74,
      "temporal_lower_bound": 64,
      "ratio": 1.15625,
      "runtime_seconds": 0.550874707998446,
      "restarts": 283
    },
    {
      "instance": "PSP223",
      "status": "feasible",
      "makespan": 92,
      "temporal_lower_bound": 42,
      "ratio": 2.1904761904761907,
      "runtime_seconds": 0.5566039999976056,
      "restarts": 1
    },
    {
      "instance": "PSP224",
      "status": "feasible",
      "makespan": 91,
      "temporal_lower_bound": 74,
      "ratio": 1.2297297297297298,
      "runtime_seconds": 0.5509602499987523,
      "restarts": 257
    },
    {
      "instance": "PSP225",
      "status": "infeasible",
      "makespan": null,
      "temporal_lower_bound": 33,
      "ratio": null,
      "runtime_seconds": 6.54579998808913e-05,
      "restarts": 0
    },
    {
      "instance": "PSP226",
      "status": "feasible",
      "makespan": 68,
      "temporal_lower_bound": 62,
      "ratio": 1.096774193548387,
      "runtime_seconds": 0.5514164999985951,
      "restarts": 409
    },
    {
      "instance": "PSP227",
      "status": "feasible",
      "makespan": 59,
      "temporal_lower_bound": 59,
      "ratio": 1.0,
      "runtime_seconds": 0.0006462499986810144,
      "restarts": 1
    },
    {
      "instance": "PSP228",
      "status": "feasible",
      "makespan": 50,
      "temporal_lower_bound": 38,
      "ratio": 1.3157894736842106,
      "runtime_seconds": 0.5513084580015857,
      "restarts": 341
    },
    {
      "instance": "PSP229",
      "status": "feasible",
      "makespan": 73,
      "temporal_lower_bound": 64,
      "ratio": 1.140625,
      "runtime_seconds": 0.20393662500282517,
      "restarts": 0
    },
    {
      "instance": "PSP23",
      "status": "feasible",
      "makespan": 34,
      "temporal_lower_bound": 34,
      "ratio": 1.0,
      "runtime_seconds": 0.0008949160001066048,
      "restarts": 1
    },
    {
      "instance": "PSP230",
      "status": "feasible",
      "makespan": 58,
      "temporal_lower_bound": 51,
      "ratio": 1.1372549019607843,
      "runtime_seconds": 0.552962124998885,
      "restarts": 144
    },
    {
      "instance": "PSP231",
      "status": "feasible",
      "makespan": 51,
      "temporal_lower_bound": 49,
      "ratio": 1.0408163265306123,
      "runtime_seconds": 0.550564499997563,
      "restarts": 356
    },
    {
      "instance": "PSP232",
      "status": "feasible",
      "makespan": 46,
      "temporal_lower_bound": 46,
      "ratio": 1.0,
      "runtime_seconds": 0.20439312500093365,
      "restarts": 0
    },
    {
      "instance": "PSP233",
      "status": "feasible",
      "makespan": 56,
      "temporal_lower_bound": 47,
      "ratio": 1.1914893617021276,
      "runtime_seconds": 0.550459417001548,
      "restarts": 444
    },
    {
      "instance": "PSP234",
      "status": "infeasible",
      "makespan": null,
      "temporal_lower_bound": 37,
      "ratio": null,
      "runtime_seconds": 5.687500015483238e-05,
      "restarts": 0
    },
    {
      "instance": "PSP235",
      "status": "feasible",
      "makespan": 43,
      "temporal_lower_bound": 36,
      "ratio": 1.1944444444444444,
      "runtime_seconds": 0.5502597080012492,
      "restarts": 427
    },
    {
      "instance": "PSP236",
      "status": "feasible",
      "makespan": 36,
      "temporal_lower_bound": 34,
      "ratio": 1.0588235294117647,
      "runtime_seconds": 0.5506422920007026,
      "restarts": 499
    },
    {
      "instance": "PSP237",
      "status": "infeasible",
      "makespan": null,
      "temporal_lower_bound": 49,
      "ratio": null,
      "runtime_seconds": 7.337499846471474e-05,
      "restarts": 0
    },
    {
      "instance": "PSP238",
      "status": "feasible",
      "makespan": 49,
      "temporal_lower_bound": 32,
      "ratio": 1.53125,
      "runtime_seconds": 0.5508059999992838,
      "restarts": 417
    },
    {
      "instance": "PSP239",
      "status": "infeasible",
      "makespan": null,
      "temporal_lower_bound": 60,
      "ratio": null,
      "runtime_seconds": 1.3249999028630555e-05,
      "restarts": 0
    },
    {
      "instance": "PSP24",
      "status": "feasible",
      "makespan": 33,
      "temporal_lower_bound": 33,
      "ratio": 1.0,
      "runtime_seconds": 0.00031237499933922663,
      "restarts": 1
    },
    {
      "instance": "PSP240",
      "status": "feasible",
      "makespan": 47,
      "temporal_lower_bound": 46,
      "ratio": 1.0217391304347827,
      "runtime_seconds": 0.5505135000021255,
      "restarts": 376
    },
    {
      "instance": "PSP241",
      "status": "feasible",
      "makespan": 94,
      "temporal_lower_bound": 79,
      "ratio": 1.1898734177215189,
      "runtime_seconds": 0.5506403340004908,
      "restarts": 332
    },
    {
      "instance": "PSP242",
      "status": "feasible",
      "makespan": 70,
      "temporal_lower_bound": 55,
      "ratio": 1.2727272727272727,
      "runtime_seconds": 0.5568689579995407,
      "restarts": 10
    },
    {
      "instance": "PSP243",
      "status": "infeasible",
      "makespan": null,
      "temporal_lower_bound": 30,
      "ratio": null,
      "runtime_seconds": 0.20307145900005708,
      "restarts": 0
    },
    {
      "instance": "PSP244",
      "status": "infeasible",
      "makespan": null,
      "temporal_lower_bound": 54,
      "ratio": null,
      "runtime_seconds": 6.841600043117069e-05,
      "restarts": 0
    },
    {
      "instance": "PSP245",
      "status": "infeasible",
      "makespan": null,
      "temporal_lower_bound": 39,
      "ratio": null,
      "runtime_seconds": 5.983300070511177e-05,
      "restarts": 0
    },
    {
      "instance": "PSP246",
      "status": "infeasible",
      "makespan": null,
      "temporal_lower_bound": 25,
      "ratio": null,
      "runtime_seconds": 5.020800017518923e-05,
      "restarts": 0
    },
    {
      "instance": "PSP247",
      "status": "infeasible",
      "makespan": null,
      "temporal_lower_bound": 38,
      "ratio": null,
      "runtime_seconds": 5.541700011235662e-05,
      "restarts": 0
    },
    {
      "instance": "PSP248",
      "status": "feasible",
      "makespan": 65,
      "temporal_lower_bound": 45,
      "ratio": 1.4444444444444444,
      "runtime_seconds": 0.5523662500017963,
      "restarts": 311
    },
    {
      "instance": "PSP249",
      "status": "feasible",
      "makespan": 61,
      "temporal_lower_bound": 53,
      "ratio": 1.150943396226415,
      "runtime_seconds": 0.5507757919986034,
      "restarts": 410
    },
    {
      "instance": "PSP25",
      "status": "feasible",
      "makespan": 40,
      "temporal_lower_bound": 35,
      "ratio": 1.1428571428571428,
      "runtime_seconds": 0.5562161669986381,
      "restarts": 1
    },
    {
      "instance": "PSP250",
      "status": "infeasible",
      "makespan": null,
      "temporal_lower_bound": 57,
      "ratio": null,
      "runtime_seconds": 5.1250000979052857e-05,
      "restarts": 0
    },
    {
      "instance": "PSP251",
      "status": "feasible",
      "makespan": 61,
      "temporal_lower_bound": 50,
      "ratio": 1.22,
      "runtime_seconds": 0.5532736670029408,
      "restarts": 335
    },
    {
      "instance": "PSP252",
      "status": "infeasible",
      "makespan": null,
      "temporal_lower_bound": 60,
      "ratio": null,
      "runtime_seconds": 0.20215662500049802,
      "restarts": 0
    },
    {
      "instance": "PSP253",
      "status": "infeasible",
      "makespan": null,
      "temporal_lower_bound": 21,
      "ratio": null,
      "runtime_seconds": 5.166700066183694e-05,
      "restarts": 0
    },
    {
      "instance": "PSP254",
      "status": "infeasible",
      "makespan": null,
      "temporal_lower_bound": 47,
      "ratio": null,
      "runtime_seconds": 5.8000001445179805e-05,
      "restarts": 0
    },
    {
      "instance": "PSP255",
      "status": "feasible",
      "makespan": 48,
      "temporal_lower_bound": 29,
      "ratio": 1.6551724137931034,
      "runtime_seconds": 0.5525679999991553,
      "restarts": 333
    },
    {
      "instance": "PSP256",
      "status": "feasible",
      "makespan": 52,
      "temporal_lower_bound": 31,
      "ratio": 1.6774193548387097,
      "runtime_seconds": 0.5510151669986953,
      "restarts": 323
    },
    {
      "instance": "PSP257",
      "status": "feasible",
      "makespan": 60,
      "temporal_lower_bound": 52,
      "ratio": 1.1538461538461537,
      "runtime_seconds": 0.5511597909971897,
      "restarts": 370
    },
    {
      "instance": "PSP258",
      "status": "infeasible",
      "makespan": null,
      "temporal_lower_bound": 43,
      "ratio": null,
      "runtime_seconds": 5.020800017518923e-05,
      "restarts": 0
    },
    {
      "instance": "PSP259",
      "status": "feasible",
      "makespan": 45,
      "temporal_lower_bound": 22,
      "ratio": 2.0454545454545454,
      "runtime_seconds": 0.551144541001122,
      "restarts": 416
    },
    {
      "instance": "PSP26",
      "status": "infeasible",
      "makespan": null,
      "temporal_lower_bound": 54,
      "ratio": null,
      "runtime_seconds": 1.4833000022917986e-05,
      "restarts": 0
    },
    {
      "instance": "PSP260",
      "status": "feasible",
      "makespan": 32,
      "temporal_lower_bound": 18,
      "ratio": 1.7777777777777777,
      "runtime_seconds": 0.20441820800260757,
      "restarts": 0
    },
    {
      "instance": "PSP261",
      "status": "infeasible",
      "makespan": null,
      "temporal_lower_bound": 46,
      "ratio": null,
      "runtime_seconds": 5.0917002226924524e-05,
      "restarts": 0
    },
    {
      "instance": "PSP262",
      "status": "feasible",
      "makespan": 63,
      "temporal_lower_bound": 58,
      "ratio": 1.0862068965517242,
      "runtime_seconds": 0.5521994580012688,
      "restarts": 357
    },
    {
      "instance": "PSP263",
      "status": "feasible",
      "makespan": 64,
      "temporal_lower_bound": 56,
      "ratio": 1.1428571428571428,
      "runtime_seconds": 0.5508042090004892,
      "restarts": 286
    },
    {
      "instance": "PSP264",
      "status": "feasible",
      "makespan": 78,
      "temporal_lower_bound": 68,
      "ratio": 1.1470588235294117,
      "runtime_seconds": 0.5506046250011423,
      "restarts": 272
    },
    {
      "instance": "PSP265",
      "status": "infeasible",
      "makespan": null,
      "temporal_lower_bound": 37,
      "ratio": null,
      "runtime_seconds": 0.0002717499992286321,
      "restarts": 0
    },
    {
      "instance": "PSP266",
      "status": "infeasible",
      "makespan": null,
      "temporal_lower_bound": 53,
      "ratio": null,
      "runtime_seconds": 7.391600229311734e-05,
      "restarts": 0
    },
    {
      "instance": "PSP267",
      "status": "feasible",
      "makespan": 60,
      "temporal_lower_bound": 57,
      "ratio": 1.0526315789473684,
      "runtime_seconds": 0.5505193339995458,
      "restarts": 333
    },
    {
      "instance": "PSP268",
      "status": "feasible",
      "makespan": 36,
      "temporal_lower_bound": 28,
      "ratio": 1.2857142857142858,
      "runtime_seconds": 0.5508862919996318,
      "restarts": 399
    },
    {
      "instance": "PSP269",
      "status": "feasible",
      "makespan": 35,
      "temporal_lower_bound": 34,
      "ratio": 1.0294117647058822,
      "runtime_seconds": 0.5503002500008733,
      "restarts": 487
    },
    {
      "instance": "PSP27",
      "status": "infeasible",
      "makespan": null,
      "temporal_lower_bound": 40,
      "ratio": null,
      "runtime_seconds": 1.270900247618556e-05,
      "restarts": 0
    },
    {
      "instance": "PSP270",
      "status": "feasible",
      "makespan": 75,
      "temporal_lower_bound": 52,
      "ratio": 1.4423076923076923,
      "runtime_seconds": 0.20637400000123307,
      "restarts": 0
    },
    {
      "instance": "PSP28",
      "status": "feasible",
      "makespan": 34,
      "temporal_lower_bound": 31,
      "ratio": 1.096774193548387,
      "runtime_seconds": 0.5508488749983371,
      "restarts": 588
    },
    {
      "instance": "PSP29",
      "status": "feasible",
      "makespan": 32,
      "temporal_lower_bound": 26,
      "ratio": 1.2307692307692308,
      "runtime_seconds": 0.5514453329997195,
      "restarts": 434
    },
    {
      "instance": "PSP3",
      "status": "feasible",
      "makespan": 36,
      "temporal_lower_bound": 28,
      "ratio": 1.2857142857142858,
      "runtime_seconds": 0.557067083002039,
      "restarts": 314
    },
    {
      "instance": "PSP30",
      "status": "feasible",
      "makespan": 32,
      "temporal_lower_bound": 23,
      "ratio": 1.391304347826087,
      "runtime_seconds": 0.20462441599738668,
      "restarts": 0
    },
    {
      "instance": "PSP31",
      "status": "infeasible",
      "makespan": null,
      "temporal_lower_bound": 27,
      "ratio": null,
      "runtime_seconds": 5.2292001782916486e-05,
      "restarts": 0
    },
    {
      "instance": "PSP32",
      "status": "infeasible",
      "makespan": null,
      "temporal_lower_bound": 46,
      "ratio": null,
      "runtime_seconds": 5.1416998758213595e-05,
      "restarts": 0
    },
    {
      "instance": "PSP33",
      "status": "feasible",
      "makespan": 70,
      "temporal_lower_bound": 24,
      "ratio": 2.9166666666666665,
      "runtime_seconds": 0.7921899169996323,
      "restarts": 212
    },
    {
      "instance": "PSP34",
      "status": "feasible",
      "makespan": 58,
      "temporal_lower_bound": 21,
      "ratio": 2.761904761904762,
      "runtime_seconds": 0.2838492079972639,
      "restarts": 0
    },
    {
      "instance": "PSP35",
      "status": "feasible",
      "makespan": 45,
      "temporal_lower_bound": 26,
      "ratio": 1.7307692307692308,
      "runtime_seconds": 0.590209624999261,
      "restarts": 300
    },
    {
      "instance": "PSP36",
      "status": "feasible",
      "makespan": 55,
      "temporal_lower_bound": 26,
      "ratio": 2.1153846153846154,
      "runtime_seconds": 0.20582137500241515,
      "restarts": 0
    },
    {
      "instance": "PSP37",
      "status": "feasible",
      "makespan": 32,
      "temporal_lower_bound": 24,
      "ratio": 1.3333333333333333,
      "runtime_seconds": 0.5571979579981416,
      "restarts": 379
    },
    {
      "instance": "PSP38",
      "status": "feasible",
      "makespan": 45,
      "temporal_lower_bound": 20,
      "ratio": 2.25,
      "runtime_seconds": 0.5737279579989263,
      "restarts": 220
    },
    {
      "instance": "PSP39",
      "status": "feasible",
      "makespan": 49,
      "temporal_lower_bound": 37,
      "ratio": 1.3243243243243243,
      "runtime_seconds": 0.5564797500010172,
      "restarts": 301
    },
    {
      "instance": "PSP4",
      "status": "feasible",
      "makespan": 39,
      "temporal_lower_bound": 29,
      "ratio": 1.3448275862068966,
      "runtime_seconds": 0.5533361669986334,
      "restarts": 275
    },
    {
      "instance": "PSP40",
      "status": "infeasible",
      "makespan": null,
      "temporal_lower_bound": 22,
      "ratio": null,
      "runtime_seconds": 5.2874998800689355e-05,
      "restarts": 0
    },
    {
      "instance": "PSP41",
      "status": "infeasible",
      "makespan": null,
      "temporal_lower_bound": 31,
      "ratio": null,
      "runtime_seconds": 4.8417001380585134e-05,
      "restarts": 0
    },
    {
      "instance": "PSP42",
      "status": "infeasible",
      "makespan": null,
      "temporal_lower_bound": 25,
      "ratio": null,
      "runtime_seconds": 0.20201558299959288,
      "restarts": 0
    },
    {
      "instance": "PSP43",
      "status": "feasible",
      "makespan": 32,
      "temporal_lower_bound": 23,
      "ratio": 1.391304347826087,
      "runtime_seconds": 0.5520870830005151,
      "restarts": 420
    },
    {
      "instance": "PSP44",
      "status": "feasible",
      "makespan": 37,
      "temporal_lower_bound": 21,
      "ratio": 1.7619047619047619,
      "runtime_seconds": 0.5544442499995057,
      "restarts": 314
    },
    {
      "instance": "PSP45",
      "status": "feasible",
      "makespan": 36,
      "temporal_lower_bound": 25,
      "ratio": 1.44,
      "runtime_seconds": 0.5537147080030991,
      "restarts": 328
    },
    {
      "instance": "PSP46",
      "status": "feasible",
      "makespan": 32,
      "temporal_lower_bound": 27,
      "ratio": 1.1851851851851851,
      "runtime_seconds": 0.5560107910023362,
      "restarts": 359
    },
    {
      "instance": "PSP47",
      "status": "feasible",
      "makespan": 35,
      "temporal_lower_bound": 31,
      "ratio": 1.1290322580645162,
      "runtime_seconds": 0.5515124590019695,
      "restarts": 308
    },
    {
      "instance": "PSP48",
      "status": "infeasible",
      "makespan": null,
      "temporal_lower_bound": 40,
      "ratio": null,
      "runtime_seconds": 5.895800131838769e-05,
      "restarts": 0
    },
    {
      "instance": "PSP49",
      "status": "feasible",
      "makespan": 27,
      "temporal_lower_bound": 22,
      "ratio": 1.2272727272727273,
      "runtime_seconds": 0.5556757500016829,
      "restarts": 1
    },
    {
      "instance": "PSP5",
      "status": "feasible",
      "makespan": 32,
      "temporal_lower_bound": 22,
      "ratio": 1.4545454545454546,
      "runtime_seconds": 0.20398983400082216,
      "restarts": 0
    },
    {
      "instance": "PSP50",
      "status": "feasible",
      "makespan": 68,
      "temporal_lower_bound": 46,
      "ratio": 1.4782608695652173,
      "runtime_seconds": 0.5610319170009461,
      "restarts": 202
    },
    {
      "instance": "PSP51",
      "status": "infeasible",
      "makespan": null,
      "temporal_lower_bound": 33,
      "ratio": null,
      "runtime_seconds": 1.166700167232193e-05,
      "restarts": 0
    },
    {
      "instance": "PSP52",
      "status": "feasible",
      "makespan": 31,
      "temporal_lower_bound": 25,
      "ratio": 1.24,
      "runtime_seconds": 0.5540807499965013,
      "restarts": 521
    },
    {
      "instance": "PSP53",
      "status": "feasible",
      "makespan": 36,
      "temporal_lower_bound": 30,
      "ratio": 1.2,
      "runtime_seconds": 0.551210749999882,
      "restarts": 360
    },
    {
      "instance": "PSP54",
      "status": "feasible",
      "makespan": 32,
      "temporal_lower_bound": 27,
      "ratio": 1.1851851851851851,
      "runtime_seconds": 0.5535028749982303,
      "restarts": 338
    },
    {
      "instance": "PSP55",
      "status": "infeasible",
      "makespan": null,
      "temporal_lower_bound": 12,
      "ratio": null,
      "runtime_seconds": 4.762500248034485e-05,
      "restarts": 0
    },
    {
      "instance": "PSP56",
      "status": "feasible",
      "makespan": 34,
      "temporal_lower_bound": 33,
      "ratio": 1.0303030303030303,
      "runtime_seconds": 0.5504287910007406,
      "restarts": 654
    },
    {
      "instance": "PSP57",
      "status": "feasible",
      "makespan": 40,
      "temporal_lower_bound": 36,
      "ratio": 1.1111111111111112,
      "runtime_seconds": 0.5509484579997661,
      "restarts": 482
    },
    {
      "instance": "PSP58",
      "status": "feasible",
      "makespan": 20,
      "temporal_lower_bound": 19,
      "ratio": 1.0526315789473684,
      "runtime_seconds": 0.5506825420015957,
      "restarts": 647
    },
    {
      "instance": "PSP59",
      "status": "feasible",
      "makespan": 37,
      "temporal_lower_bound": 25,
      "ratio": 1.48,
      "runtime_seconds": 0.5538339590020769,
      "restarts": 509
    },
    {
      "instance": "PSP6",
      "status": "infeasible",
      "makespan": null,
      "temporal_lower_bound": 22,
      "ratio": null,
      "runtime_seconds": 5.679099922417663e-05,
      "restarts": 0
    },
    {
      "instance": "PSP60",
      "status": "feasible",
      "makespan": 37,
      "temporal_lower_bound": 37,
      "ratio": 1.0,
      "runtime_seconds": 0.00047766700299689546,
      "restarts": 1
    },
    {
      "instance": "PSP61",
      "status": "infeasible",
      "makespan": null,
      "temporal_lower_bound": 32,
      "ratio": null,
      "runtime_seconds": 4.416699812281877e-05,
      "restarts": 0
    },
    {
      "instance": "PSP62",
      "status": "feasible",
      "makespan": 54,
      "temporal_lower_bound": 35,
      "ratio": 1.542857142857143,
      "runtime_seconds": 0.22922795799968299,
      "restarts": 0
    },
    {
      "instance": "PSP63",
      "status": "feasible",
      "makespan": 67,
      "temporal_lower_bound": 34,
      "ratio": 1.9705882352941178,
      "runtime_seconds": 0.2557779169983405,
      "restarts": 0
    },
    {
      "instance": "PSP64",
      "status": "feasible",
      "makespan": 47,
      "temporal_lower_bound": 18,
      "ratio": 2.611111111111111,
      "runtime_seconds": 0.2701117079996038,
      "restarts": 0
    },
    {
      "instance": "PSP65",
      "status": "feasible",
      "makespan": 49,
      "temporal_lower_bound": 19,
      "ratio": 2.5789473684210527,
      "runtime_seconds": 1.0000398750016757,
      "restarts": 1
    },
    {
      "instance": "PSP66",
      "status": "infeasible",
      "makespan": null,
      "temporal_lower_bound": 28,
      "ratio": null,
      "runtime_seconds": 5.962500290479511e-05,
      "restarts": 0
    },
    {
      "instance": "PSP67",
      "status": "infeasible",
      "makespan": null,
      "temporal_lower_bound": 34,
      "ratio": null,
      "runtime_seconds": 3.941600152757019e-05,
      "restarts": 0
    },
    {
      "instance": "PSP68",
      "status": "infeasible",
      "makespan": null,
      "temporal_lower_bound": 17,
      "ratio": null,
      "runtime_seconds": 4.3000000005122274e-05,
      "restarts": 0
    },
    {
      "instance": "PSP69",
      "status": "feasible",
      "makespan": 46,
      "temporal_lower_bound": 42,
      "ratio": 1.0952380952380953,
      "runtime_seconds": 0.5511403750024328,
      "restarts": 437
    },
    {
      "instance": "PSP7",
      "status": "feasible",
      "makespan": 43,
      "temporal_lower_bound": 38,
      "ratio": 1.131578947368421,
      "runtime_seconds": 0.5511228750001465,
      "restarts": 443
    },
    {
      "instance": "PSP70",
      "status": "feasible",
      "makespan": 54,
      "temporal_lower_bound": 28,
      "ratio": 1.9285714285714286,
      "runtime_seconds": 0.22210604199790396,
      "restarts": 0
    },
    {
      "instance": "PSP71",
      "status": "infeasible",
      "makespan": null,
      "temporal_lower_bound": 32,
      "ratio": null,
      "runtime_seconds": 4.7375000576721504e-05,
      "restarts": 0
    },
    {
      "instance": "PSP72",
      "status": "infeasible",
      "makespan": null,
      "temporal_lower_bound": 29,
      "ratio": null,
      "runtime_seconds": 4.3708998418878764e-05,
      "restarts": 0
    },
    {
      "instance": "PSP73",
      "status": "feasible",
      "makespan": 31,
      "temporal_lower_bound": 26,
      "ratio": 1.1923076923076923,
      "runtime_seconds": 0.5506710410008964,
      "restarts": 376
    },
    {
      "instance": "PSP74",
      "status": "infeasible",
      "makespan": null,
      "temporal_lower_bound": 22,
      "ratio": null,
      "runtime_seconds": 4.837500091525726e-05,
      "restarts": 0
    },
    {
      "instance": "PSP75",
      "status": "feasible",
      "makespan": 28,
      "temporal_lower_bound": 21,
      "ratio": 1.3333333333333333,
      "runtime_seconds": 0.555746416997863,
      "restarts": 369
    },
    {
      "instance": "PSP76",
      "status": "infeasible",
      "makespan": null,
      "temporal_lower_bound": 47,
      "ratio": null,
      "runtime_seconds": 4.3082996853627264e-05,
      "restarts": 0
    },
    {
      "instance": "PSP77",
      "status": "feasible",
      "makespan": 56,
      "temporal_lower_bound": 38,
      "ratio": 1.4736842105263157,
      "runtime_seconds": 0.5587054169991461,
      "restarts": 230
    },
    {
      "instance": "PSP78",
      "status": "feasible",
      "makespan": 26,
      "temporal_lower_bound": 26,
      "ratio": 1.0,
      "runtime_seconds": 0.20036920799975633,
      "restarts": 324
    },
    {
      "instance": "PSP79",
      "status": "feasible",
      "makespan": 30,
      "temporal_lower_bound": 30,
      "ratio": 1.0,
      "runtime_seconds": 0.5562456660009047,
      "restarts": 380
    },
    {
      "instance": "PSP8",
      "status": "feasible",
      "makespan": 40,
      "temporal_lower_bound": 33,
      "ratio": 1.2121212121212122,
      "runtime_seconds": 0.5513790000004519,
      "restarts": 363
    },
    {
      "instance": "PSP80",
      "status": "feasible",
      "makespan": 40,
      "temporal_lower_bound": 31,
      "ratio": 1.2903225806451613,
      "runtime_seconds": 0.5534235000013723,
      "restarts": 539
    },
    {
      "instance": "PSP81",
      "status": "feasible",
      "makespan": 26,
      "temporal_lower_bound": 15,
      "ratio": 1.7333333333333334,
      "runtime_seconds": 0.5534609589994943,
      "restarts": 416
    },
    {
      "instance": "PSP82",
      "status": "feasible",
      "makespan": 16,
      "temporal_lower_bound": 16,
      "ratio": 1.0,
      "runtime_seconds": 0.5501614169988898,
      "restarts": 765
    },
    {
      "instance": "PSP83",
      "status": "feasible",
      "makespan": 25,
      "temporal_lower_bound": 25,
      "ratio": 1.0,
      "runtime_seconds": 0.00045991599836270325,
      "restarts": 1
    },
    {
      "instance": "PSP84",
      "status": "feasible",
      "makespan": 47,
      "temporal_lower_bound": 47,
      "ratio": 1.0,
      "runtime_seconds": 0.553144000001339,
      "restarts": 439
    },
    {
      "instance": "PSP85",
      "status": "feasible",
      "makespan": 23,
      "temporal_lower_bound": 23,
      "ratio": 1.0,
      "runtime_seconds": 0.00044666699977824464,
      "restarts": 1
    },
    {
      "instance": "PSP86",
      "status": "feasible",
      "makespan": 46,
      "temporal_lower_bound": 34,
      "ratio": 1.3529411764705883,
      "runtime_seconds": 0.551298833997862,
      "restarts": 354
    },
    {
      "instance": "PSP87",
      "status": "feasible",
      "makespan": 35,
      "temporal_lower_bound": 32,
      "ratio": 1.09375,
      "runtime_seconds": 0.5540252910031995,
      "restarts": 563
    },
    {
      "instance": "PSP88",
      "status": "feasible",
      "makespan": 43,
      "temporal_lower_bound": 26,
      "ratio": 1.6538461538461537,
      "runtime_seconds": 0.5597658330007107,
      "restarts": 1
    },
    {
      "instance": "PSP89",
      "status": "feasible",
      "makespan": 53,
      "temporal_lower_bound": 45,
      "ratio": 1.1777777777777778,
      "runtime_seconds": 0.5506868329975987,
      "restarts": 487
    },
    {
      "instance": "PSP9",
      "status": "feasible",
      "makespan": 45,
      "temporal_lower_bound": 29,
      "ratio": 1.5517241379310345,
      "runtime_seconds": 0.5654808750005031,
      "restarts": 269
    },
    {
      "instance": "PSP90",
      "status": "feasible",
      "makespan": 49,
      "temporal_lower_bound": 49,
      "ratio": 1.0,
      "runtime_seconds": 0.554202625000471,
      "restarts": 384
    },
    {
      "instance": "PSP91",
      "status": "feasible",
      "makespan": 47,
      "temporal_lower_bound": 34,
      "ratio": 1.3823529411764706,
      "runtime_seconds": 0.2029267500001879,
      "restarts": 0
    },
    {
      "instance": "PSP92",
      "status": "infeasible",
      "makespan": null,
      "temporal_lower_bound": 81,
      "ratio": null,
      "runtime_seconds": 4.875000013271347e-05,
      "restarts": 0
    },
    {
      "instance": "PSP93",
      "status": "infeasible",
      "makespan": null,
      "temporal_lower_bound": 31,
      "ratio": null,
      "runtime_seconds": 5.7666999055072665e-05,
      "restarts": 0
    },
    {
      "instance": "PSP94",
      "status": "feasible",
      "makespan": 33,
      "temporal_lower_bound": 25,
      "ratio": 1.32,
      "runtime_seconds": 0.5509527499998512,
      "restarts": 449
    },
    {
      "instance": "PSP95",
      "status": "feasible",
      "makespan": 47,
      "temporal_lower_bound": 31,
      "ratio": 1.5161290322580645,
      "runtime_seconds": 0.5515190410005744,
      "restarts": 415
    },
    {
      "instance": "PSP96",
      "status": "feasible",
      "makespan": 52,
      "temporal_lower_bound": 33,
      "ratio": 1.5757575757575757,
      "runtime_seconds": 0.5509441249996598,
      "restarts": 379
    },
    {
      "instance": "PSP97",
      "status": "feasible",
      "makespan": 61,
      "temporal_lower_bound": 61,
      "ratio": 1.0,
      "runtime_seconds": 0.000417291001213016,
      "restarts": 1
    },
    {
      "instance": "PSP98",
      "status": "infeasible",
      "makespan": null,
      "temporal_lower_bound": 51,
      "ratio": null,
      "runtime_seconds": 5.3291998483473435e-05,
      "restarts": 0
    },
    {
      "instance": "PSP99",
      "status": "feasible",
      "makespan": 42,
      "temporal_lower_bound": 27,
      "ratio": 1.5555555555555556,
      "runtime_seconds": 0.5513878329984436,
      "restarts": 373
    }
  ]
}